chatgpt_query.py
chatgpt_query-0.1.0.dist-info/licenses/LICENSE
chatgpt_query-0.1.0.dist-info/METADATA
chatgpt_query-0.1.0.dist-info/WHEEL
chatgpt_query-0.1.0.dist-info/entry_points.txt
chatgpt_query-0.1.0.dist-info/top_level.txt
chatgpt_query-0.1.0.dist-info/RECORD
