Metadata-Version: 2.4
Name: chatgpt-query
Version: 0.1.0
Summary: A simple chat interface tool
Author-email: Andrej730 <andrej730@icloud.com>
Maintainer-email: Andrej730 <andrej730@icloud.com>
License-Expression: MIT
Project-URL: Homepage, https://github.com/Andrej730/chatgpt-query
Project-URL: Repository, https://github.com/Andrej730/chatgpt-query
Project-URL: Issues, https://github.com/Andrej730/chatgpt-query/issues
Keywords: chat,ai,chatgpt,query,cli
Classifier: Development Status :: 3 - Alpha
Classifier: Intended Audience :: Developers
Classifier: Operating System :: OS Independent
Classifier: Programming Language :: Python :: 3
Classifier: Programming Language :: Python :: 3.9
Classifier: Programming Language :: Python :: 3.10
Classifier: Programming Language :: Python :: 3.11
Classifier: Programming Language :: Python :: 3.12
Requires-Python: >=3.9
License-File: LICENSE
Requires-Dist: typed-argparse
Provides-Extra: dev
Requires-Dist: black; extra == "dev"
Requires-Dist: ruff; extra == "dev"
Dynamic: license-file
